keep_dict_sorted.py
keep_dict_sorted-1.0.dist-info/LICENSE
keep_dict_sorted-1.0.dist-info/METADATA
keep_dict_sorted-1.0.dist-info/WHEEL
keep_dict_sorted-1.0.dist-info/top_level.txt
keep_dict_sorted-1.0.dist-info/RECORD
