Metadata-Version: 2.1
Name: keep-dict-sorted
Version: 1.0
Summary: An ordered dict with sorting capabilities.
Author-email: Benedict Verhegghe <bverheg@gmail.com>
Classifier: Programming Language :: Python :: 3
Classifier: License :: OSI Approved :: GNU General Public License v3 or later (GPLv3+)
Classifier: Development Status :: 5 - Production/Stable
Requires-Python: >=3.9
License-File: LICENSE
